{"generations": [{"label": "warmup", "sent": 974166, "urgent": 295447, "optimistic": 678034, "shed": 685, "accepted": 739605, "forged": 441753, "evicted": 207145, "orphaned": 49, "flushed": 79824, "acceptedUrgent": 216769, "acceptedOptimistic": 522836, "evictedUrgent": 207145, "evictedOptimistic": 0, "orphanedUrgent": 49, "orphanedOptimistic": 0, "flushedUrgent": 0, "flushedOptimistic": 79824, "doneUrgent": 214228, "doneOptimistic": 514543, "firstSeen": 1783935212.0, "lastSeen": 1783948031.0, "waiting": 10834, "waitingUrgent": 2541, "waitingOptimistic": 8293}], "updated": 1783948031.1120892}